dataskipper_boat/__init__.py
dataskipper_boat/emqxsl-ca.crt
dataskipper_boat/main.py
src/__init__.py
src/config/__init__.py
src/config/meter_registry.yaml
src/interfaces/__init__.py
src/interfaces/modbus_client.py
src/interfaces/notifier.py
src/interfaces/storage.py
src/models/__init__.py
src/models/alert.py
src/models/device.py
src/models/gateway_config.py
src/models/measurement.py
src/models/modbus_types.py
src/models/mqtt_trigger.py
src/services/__init__.py
src/services/aggregation_service.py
src/services/api_service.py
src/services/cached_modbus_handler.py
src/services/diagnostic_service.py
src/services/meter_registry.py
src/services/modbus_tcp_server.py
src/services/mqtt_service.py
src/services/mqtt_trigger_service.py
src/services/ntp_service.py
src/services/performance_monitor.py
src/services/register_cache.py
src/services/register_planner.py
src/services/test_mode_service.py
src/services/watchdog_service.py
src/services/weather_service.py
src/services/modbus/__init__.py
src/services/modbus/serial_client.py
src/services/modbus/tcp_client.py
src/services/notifiers/__init__.py
src/services/notifiers/discord_notifier.py
src/services/notifiers/telegram_notifier.py
src/services/storage/__init__.py
src/services/storage/file_storage.py
src/utils/__init__.py
src/utils/alert_checker.py
src/utils/common.py
src/utils/logging_config.py
src/utils/modbus_utils.py
src/utils/register_parser.py
src/web_portal/__init__.py
src/web_portal/app.py
src/web_portal/auth.py
src/web_portal/run_portal.py
src/web_portal/static/css/style.css
src/web_portal/static/js/main.js
src/web_portal/static/js/sw.js
src/web_portal/templates/alerts.html
src/web_portal/templates/base.html
src/web_portal/templates/config.html
src/web_portal/templates/config_comm_editor.html
src/web_portal/templates/config_editor.html
src/web_portal/templates/config_slave_editor.html
src/web_portal/templates/config_wizard.html
src/web_portal/templates/dashboard.html
src/web_portal/templates/devices.html
dataskipper_boat-1.2.2.dist-info/METADATA
dataskipper_boat-1.2.2.dist-info/WHEEL
dataskipper_boat-1.2.2.dist-info/entry_points.txt
dataskipper_boat-1.2.2.dist-info/top_level.txt
dataskipper_boat-1.2.2.dist-info/RECORD
