Metadata-Version: 2.4
Name: dataskipper-boat
Version: 1.2.2
Summary: IEC61850/Modbus RTU monitoring system with web portal, config management, and data collection
Author-email: Ayush <ayush@datasailors.io>
License: Proprietary
Project-URL: Homepage, https://datasailors.io
Project-URL: Bug Reports, https://datasailors.io/contact-us.html
Project-URL: Source, https://datasailors.io
Classifier: Development Status :: 4 - Beta
Classifier: Intended Audience :: System Administrators
Classifier: License :: Other/Proprietary License
Classifier: Operating System :: POSIX :: Linux
Classifier: Programming Language :: Python :: 3
Classifier: Programming Language :: Python :: 3.8
Classifier: Programming Language :: Python :: 3.9
Classifier: Programming Language :: Python :: 3.10
Classifier: Programming Language :: Python :: 3.11
Classifier: Programming Language :: Python :: 3.12
Classifier: Topic :: System :: Monitoring
Requires-Python: >=3.8
Requires-Dist: aiohttp>=3.9.0
Requires-Dist: httpx>=0.27.0
Requires-Dist: paho-mqtt>=2.0.0
Requires-Dist: pymodbus>=3.6.0
Requires-Dist: pyserial>=3.5
Requires-Dist: pyiec61850==1.5.2a1
Requires-Dist: dataclasses-json>=0.6.0
Requires-Dist: PyYAML>=6.0
Requires-Dist: pytz>=2024.1
Requires-Dist: discord.py>=2.3.0
Requires-Dist: python-telegram-bot>=21.0
Requires-Dist: tenacity>=8.2.0
Requires-Dist: ntplib>=0.4.0
Requires-Dist: fastapi>=0.109.0
Requires-Dist: uvicorn>=0.27.0
Requires-Dist: websockets>=12.0
Requires-Dist: jinja2>=3.1.0
Requires-Dist: python-multipart>=0.0.6
Requires-Dist: psutil>=5.9.0
Provides-Extra: dev
Requires-Dist: coverage>=7.0.0; extra == "dev"
Requires-Dist: pytest>=7.0.0; extra == "dev"
Requires-Dist: pytest-asyncio>=0.21.0; extra == "dev"
Requires-Dist: pytest-cov>=4.0.0; extra == "dev"
